adasigpy/__init__.py
adasigpy/adasigpy.py
adasigpy/domain/__init__.py
adasigpy/domain/method.py
adasigpy/interface/__init__.py
adasigpy/interface/filter.py
adasigpy/method.py
adasigpy-0.1.8.dist-info/LICENSE
adasigpy-0.1.8.dist-info/WHEEL
adasigpy-0.1.8.dist-info/METADATA
adasigpy-0.1.8.dist-info/RECORD
